bh_bump/__init__.py
bh_bump/__main__.py
bh_bump/constants.py
bh_bump/note.py
bh_bump/toml.py
bh_bump/util.py
bh_bump/data/bumpversion.cfg
bh_bump/data/test_dummy.py
bh_bump-0.1.3rc1.dist-info/METADATA
bh_bump-0.1.3rc1.dist-info/WHEEL
bh_bump-0.1.3rc1.dist-info/entry_points.txt
bh_bump-0.1.3rc1.dist-info/top_level.txt
bh_bump-0.1.3rc1.dist-info/RECORD
