Metadata-Version: 2.1
Name: bh-bump
Version: 0.1.3rc1
Summary: An aid in project deployment
Author-email: Bryan Hann <nobody@nowhere.com>
Maintainer-email: Bryan Hann <nobody@nowhere.com>
License: MIT license
Project-URL: bugs, https://github.com/bryanhann/bh-bump/issues
Project-URL: changelog, https://github.com/bryanhann/bh-bump/blob/master/changelog.md
Project-URL: homepage, https://github.com/bryanhann/bh-bump
Requires-Python: >=3.12
Requires-Dist: bump2version >=1.0.1
Requires-Dist: colorama >=0.4.6
Requires-Dist: typer >=0.13.0
Provides-Extra: dev
